aws_idr_customer_cli/__init__.py
aws_idr_customer_cli/exceptions.py
aws_idr_customer_cli/main.py
aws_idr_customer_cli/clients/__init__.py
aws_idr_customer_cli/clients/ec2.py
aws_idr_customer_cli/clients/iam.py
aws_idr_customer_cli/clients/s3.py
aws_idr_customer_cli/clients/sts.py
aws_idr_customer_cli/commands/__init__.py
aws_idr_customer_cli/commands/create_alarm/__init__.py
aws_idr_customer_cli/commands/create_alarm/command.py
aws_idr_customer_cli/commands/ingest_alarms/__init__.py
aws_idr_customer_cli/commands/ingest_alarms/command.py
aws_idr_customer_cli/commands/register_workload/__init__.py
aws_idr_customer_cli/commands/register_workload/command.py
aws_idr_customer_cli/commands/setup_apm/__init__.py
aws_idr_customer_cli/commands/setup_apm/command.py
aws_idr_customer_cli/core/__init__.py
aws_idr_customer_cli/core/command_base.py
aws_idr_customer_cli/core/decorators.py
aws_idr_customer_cli/core/registry.py
aws_idr_customer_cli/core/interactive/__init__.py
aws_idr_customer_cli/core/interactive/ui.py
aws_idr_customer_cli/data_accessors/__init__.py
aws_idr_customer_cli/data_accessors/alarm_accessor.py
aws_idr_customer_cli/data_accessors/apigateway_accessor.py
aws_idr_customer_cli/data_accessors/base_accessor.py
aws_idr_customer_cli/data_accessors/cloudformation_accessor.py
aws_idr_customer_cli/data_accessors/eventbridge_accessor.py
aws_idr_customer_cli/data_accessors/logs_accessor.py
aws_idr_customer_cli/data_accessors/resource_tagging_accessor.py
aws_idr_customer_cli/data_accessors/sns_accessor.py
aws_idr_customer_cli/data_accessors/support_case_accessor.py
aws_idr_customer_cli/input/__init__.py
aws_idr_customer_cli/input/input_resource_discovery.py
aws_idr_customer_cli/interfaces/__init__.py
aws_idr_customer_cli/interfaces/file_cache_service.py
aws_idr_customer_cli/interfaces/input_service.py
aws_idr_customer_cli/interfaces/mlo_selection_manager.py
aws_idr_customer_cli/interfaces/resource_finder_service.py
aws_idr_customer_cli/models/__init__.py
awsidr-1.0.2.dist-info/METADATA
awsidr-1.0.2.dist-info/WHEEL
awsidr-1.0.2.dist-info/entry_points.txt
awsidr-1.0.2.dist-info/licenses/LICENSE.md
awsidr-1.0.2.dist-info/licenses/NOTICE.md
awsidr-1.0.2.dist-info/RECORD
