Metadata-Version: 2.4
Name: awsidr
Version: 1.0.2
License-File: LICENSE.md
License-File: NOTICE.md
Requires-Python: >=3.9
Requires-Dist: arnparse>=0.0.2
Requires-Dist: aws-lambda-powertools==3.7.0
Requires-Dist: boto3-stubs[cloudformation,cloudwatch,ec2,essential,events,iam,resourcegroupstaggingapi,sns,sts,support]==1.38.46
Requires-Dist: boto3<2.0.0,==1.34.34
Requires-Dist: click==8.1.8
Requires-Dist: colorama==0.4.6
Requires-Dist: cryptography==45.0.3
Requires-Dist: dataclasses-json==0.6.7
Requires-Dist: injector==0.21.0
Requires-Dist: pyyaml>=6.0
Requires-Dist: questionary>=2.0.0
Requires-Dist: retry==0.9.2
Requires-Dist: rich==14.0.0
